{
  "editor.suggestSelection": "first",
  "vsintellicode.modify.editor.suggestSelection": "automaticallyOverrodeDefaultValue",
  "editor.fontSize": 16,
  "workbench.iconTheme": "material-icon-theme",
  "javascript.updateImportsOnFileMove.enabled": "always",
  "go.formatTool": "goimports",
  "settingsSync.ignoredExtensions": [
  
  ],
  "typescript.updateImportsOnFileMove.enabled": "always",
  "extensions.autoUpdate": false,
  "[json]": {
  
      "editor.quickSuggestions": {
          "strings": true
      },
      "editor.suggest.insertMode": "replace"
  },
  "go.toolsManagement.autoUpdate": true,
  "gopls": {
      "experimentalWorkspaceModule": true
  },
  "prettier.jsxSingleQuote": true,
  "prettier.documentSelectors": [
      "TypeScript"
  ],
  "prettier.singleQuote": true,
  "redhat.telemetry.enabled": true,
  "workbench.colorTheme": "GitHub Dark",
  "terminal.integrated.fontFamily": "monospace",
  "editor.tabSize": 2,
  "editor.fontFamily": "Ricty Diminished",
  "window.zoomLevel": -1,
  "terminal.integrated.fontSize": 14,
  "editor.formatOnSave": true,
  "prettier.requirePragma": true
}